tg_odesli_bot/__init__.py
tg_odesli_bot/bot.py
tg_odesli_bot/platforms.py
tg_odesli_bot/schemas.py
tg_odesli_bot/settings.py
tg_odesli_bot-0.4.1.dist-info/METADATA
tg_odesli_bot-0.4.1.dist-info/WHEEL
tg_odesli_bot-0.4.1.dist-info/entry_points.txt
tg_odesli_bot-0.4.1.dist-info/licenses/LICENSE
tg_odesli_bot-0.4.1.dist-info/RECORD
