Metadata-Version: 2.4
Name: tg_odesli_bot
Version: 0.4.1
Summary: Telegram Bot to share music with Odesli (former Songlink) service.
License: GPL-3.0-only
License-File: LICENSE
Author: Mikhail Knyazev
Author-email: hellishbot@gmail.com
Requires-Python: >=3.10,<3.14
Classifier: License :: OSI Approved :: GNU General Public License v3 (GPLv3)
Classifier: Programming Language :: Python :: 3
Classifier: Programming Language :: Python :: 3.10
Classifier: Programming Language :: Python :: 3.11
Classifier: Programming Language :: Python :: 3.12
Classifier: Programming Language :: Python :: 3.13
Requires-Dist: aiocache (>=0.12.0,<0.13.0)
Requires-Dist: aiogram (<3)
Requires-Dist: aiohttp (>=3,<4)
Requires-Dist: pydantic-core (>=2.0,<3.0)
Requires-Dist: pydantic-settings (>=2,<3)
Requires-Dist: python-dotenv (>=1.0.0,<2.0.0)
Requires-Dist: sentry-sdk (>=2,<3)
Requires-Dist: spotipy (>=2.22.1,<3.0.0)
Requires-Dist: structlog (>=24.0.0,<25.0.0)
Requires-Dist: structlog-sentry (>=2.0.0,<3.0.0)
Requires-Dist: ujson (>=5.4.0,<6.0.0)
Project-URL: Homepage, https://github.com/9dogs/tg-odesli-bot
Project-URL: Repository, https://github.com/9dogs/tg-odesli-bot
